README.md
docs/adrs/README.md
snowfakery/__about__.py
snowfakery/__init__.py
snowfakery/__main__.py
snowfakery/api.py
snowfakery/cli.py
snowfakery/data_gen_exceptions.py
snowfakery/data_generator.py
snowfakery/data_generator_runtime.py
snowfakery/data_generator_runtime_object_model.py
snowfakery/generate_mapping_from_recipe.py
snowfakery/object_rows.py
snowfakery/output_streams.py
snowfakery/parse_recipe_yaml.py
snowfakery/plugins.py
snowfakery/recipe_validator.py
snowfakery/row_history.py
snowfakery/salesforce.py
snowfakery/template_funcs.py
snowfakery/backports/typeguard_context_manager_hack.py
snowfakery/cci_mapping_files/declaration_parser.py
snowfakery/cci_mapping_files/post_processes.py
snowfakery/docs/examples/evolution.yml
snowfakery/docs/examples/evolution_2.yml
snowfakery/docs/examples/formula_1.yml
snowfakery/docs/examples/gender_studies.yml
snowfakery/docs/examples/nested_counter.yml
snowfakery/docs/examples/noah.yml
snowfakery/docs/examples/person_of_interest.yml
snowfakery/docs/examples/persons_of_interest.yml
snowfakery/docs/examples/pet_stories.yml
snowfakery/docs/examples/pet_stories_2.yml
snowfakery/docs/examples/secret_life_of_pets.yml
snowfakery/docs/examples/secret_life_of_pets2.yml
snowfakery/docs/examples/simple_counters.yml
snowfakery/docs/examples/simple_static.yml
snowfakery/docs/examples/st_ives.yml
snowfakery/fakedata/fake_data_generator.py
snowfakery/fakedata/faker_validators.py
snowfakery/standard_plugins/Counters.py
snowfakery/standard_plugins/Salesforce.py
snowfakery/standard_plugins/Schedule.py
snowfakery/standard_plugins/SnowfakeryVersion.py
snowfakery/standard_plugins/UniqueId.py
snowfakery/standard_plugins/__init__.py
snowfakery/standard_plugins/_math.py
snowfakery/standard_plugins/base64.py
snowfakery/standard_plugins/datasets.py
snowfakery/standard_plugins/file.py
snowfakery/standard_plugins/statistical_distributions.py
snowfakery/tools/bench_overhead.py
snowfakery/tools/benchmark_1.yml
snowfakery/tools/mkdocs.py
snowfakery-4.2.1.dist-info/METADATA
snowfakery-4.2.1.dist-info/WHEEL
snowfakery-4.2.1.dist-info/entry_points.txt
snowfakery-4.2.1.dist-info/licenses/LICENSE
snowfakery-4.2.1.dist-info/RECORD
